azure/communication/phonenumbers/__init__.py
azure/communication/phonenumbers/_api_versions.py
azure/communication/phonenumbers/_phone_numbers_client.py
azure/communication/phonenumbers/_version.py
azure/communication/phonenumbers/py.typed
azure/communication/phonenumbers/_generated/__init__.py
azure/communication/phonenumbers/_generated/_client.py
azure/communication/phonenumbers/_generated/_configuration.py
azure/communication/phonenumbers/_generated/_patch.py
azure/communication/phonenumbers/_generated/py.typed
azure/communication/phonenumbers/_generated/_utils/__init__.py
azure/communication/phonenumbers/_generated/_utils/serialization.py
azure/communication/phonenumbers/_generated/aio/__init__.py
azure/communication/phonenumbers/_generated/aio/_client.py
azure/communication/phonenumbers/_generated/aio/_configuration.py
azure/communication/phonenumbers/_generated/aio/_patch.py
azure/communication/phonenumbers/_generated/aio/operations/__init__.py
azure/communication/phonenumbers/_generated/aio/operations/_operations.py
azure/communication/phonenumbers/_generated/aio/operations/_patch.py
azure/communication/phonenumbers/_generated/models/__init__.py
azure/communication/phonenumbers/_generated/models/_enums.py
azure/communication/phonenumbers/_generated/models/_models.py
azure/communication/phonenumbers/_generated/models/_patch.py
azure/communication/phonenumbers/_generated/operations/__init__.py
azure/communication/phonenumbers/_generated/operations/_operations.py
azure/communication/phonenumbers/_generated/operations/_patch.py
azure/communication/phonenumbers/_shared/__init__.py
azure/communication/phonenumbers/_shared/auth_policy_utils.py
azure/communication/phonenumbers/_shared/entra_token_guard_policy.py
azure/communication/phonenumbers/_shared/entra_token_guard_policy_async.py
azure/communication/phonenumbers/_shared/models.py
azure/communication/phonenumbers/_shared/policy.py
azure/communication/phonenumbers/_shared/token_exchange.py
azure_communication_phonenumbers-1.4.0.dist-info/licenses/LICENSE
azure_communication_phonenumbers-1.4.0.dist-info/METADATA
azure_communication_phonenumbers-1.4.0.dist-info/WHEEL
azure_communication_phonenumbers-1.4.0.dist-info/top_level.txt
azure_communication_phonenumbers-1.4.0.dist-info/RECORD
